{
  "game": "otr2",
  "counterType": "template",
  "matched": {
    "U:1 NY": "U_1_NY",
    "U:1 NY Mrif": "U_1_NY_Mrif",
    "U:1 RI": "U_1_RI",
    "U:11 PA": "U_11_PA",
    "U:11/91 PA": "U_11-91_PA",
    "U:12/25 NY": "U_12-25_NY",
    "U:13 PA": "U_13_PA",
    "U:2 NY": "U_2_NY",
    "U:2DE/32MA": "U_2DE-32MA",
    "U:3/4 NY": "U_3-4_NY",
    "U:3/8 PA": "U_3-8_PA",
    "U:4 PA": "U_4_PA",
    "U:4PA": "U_4PA",
    "U:5 PA": "U_5_PA",
    "U:5/6 US": "U_5-6_US",
    "U:5/6US": "U_5-6US",
    "U:59/101 NY": "U_59-101_NY",
    "U:5MD/19WI": "U_5MD-19WI",
    "U:6 PA": "U_6_PA",
    "U:67/87 PA": "U_67-87_PA",
    "U:6PA": "U_6PA",
    "U:7/69 NY": "U_7-69_NY",
    "U:71/148 NY": "U_71-148_NY",
    "U:8 IL": "U_8_IL",
    "U:8IL": "U_8IL",
    "U:93 NY": "U_93_NY",
    "U:93NY": "U_93NY",
    "U:99/115 PA": "U_99-115_PA",
    "U:Art Res-1": "U_Art_Res-1",
    "U:Art Res-2": "U_Art_Res-2",
    "U:Buchanan": "U_Buchanan",
    "U:Burnside": "Burnside",
    "U:Carroll-A": "U_Carroll-A",
    "U:Carroll-B": "U_Carroll-B",
    "U:Casey": "U_Casey",
    "U:Couch": "U_Couch",
    "U:Doubleday": "U_Doubleday",
    "U:Ferry": "U_Ferry",
    "U:Foster": "U_Foster",
    "U:Franklin": "U_Franklin",
    "U:Hamilton": "U_Hamilton",
    "U:Heintzelman": "Heintzelman",
    "U:Hooker": "U_Hooker",
    "U:Horse Art": "U_Horse_Art",
    "U:Jameson": "U_Jameson",
    "U:Kearny": "U_Kearny",
    "U:Keyes": "Keyes",
    "U:Kimball": "U_Kimball",
    "U:King": "U_King",
    "U:McCall-A": "U_McCall-A",
    "U:McCall-B": "U_McCall-B",
    "U:McClellan": "McClelland",
    "U:McDowell": "McDowell",
    "U:Meade": "U_Meade",
    "U:Meagher": "U_Meagher",
    "U:Morell": "U_Morell",
    "U:Naglee-A": "U_Naglee-A",
    "U:Naglee-B": "U_Naglee-B",
    "U:Ord": "U_Ord",
    "U:Parke": "U_Parke",
    "U:Peck-A": "U_Peck-A",
    "U:Peck-B": "U_Peck-B",
    "U:Porter": "U_Porter",
    "U:Reno": "U_Reno",
    "U:Reynolds": "U_Reynolds",
    "U:Richardson": "U_Richardson",
    "U:Ricketts": "U_Ricketts",
    "U:Robinson": "U_Robinson",
    "U:Sedgwick": "U_Sedgwick",
    "U:Seymour": "U_Seymour",
    "U:Shields": "U_Shields",
    "U:Slocum": "U_Slocum",
    "U:Smith-A": "U_Smith-A",
    "U:Smith-B": "U_Smith-B",
    "U:Stevens": "U_Stevens",
    "U:Stoneman": "U_Stoneman",
    "U:Sumner": "Sumner",
    "U:Sykes-A": "U_Sykes-A",
    "U:Sykes-B": "U_Sykes-B",
    "U:Tyler": "U_Tyler",
    "U:Viele": "U_Viele",
    "U:Warren": "U_Warren",
    "U:Weber": "U_Weber",
    "U:Wright": "U_Wright",
    "C:1 NC": "C_1_NC",
    "C:1 VA": "C_1_VA",
    "C:10 GA": "C_10_GA",
    "C:10 VA": "C_10_VA",
    "C:13 VA": "C_13_VA",
    "C:14 SC": "C_14_SC",
    "C:2 VA": "C_2_VA",
    "C:22 VA": "C_22_VA",
    "C:28 VA": "C_28_VA",
    "C:2VA": "C_2VA",
    "C:3 VA": "C_3_VA",
    "C:32 NC": "C_32_NC",
    "C:4 VA": "C_4_VA",
    "C:4 VA HA": "C_4_VA_HA",
    "C:40VA": "C_40VA",
    "C:47 VA": "C_47_VA",
    "C:4VA": "C_4VA",
    "C:5 VA": "C_5_VA",
    "C:55 VA": "C_55_VA",
    "C:56 VA": "C_56_VA",
    "C:59 VA": "C_59_VA",
    "C:60 VA": "C_60_VA",
    "C:63 VA": "C_63_VA",
    "C:7 VA": "C_7_VA",
    "C:8 VA": "C_8_VA",
    "C:9 VA": "C_9_VA",
    "C:9VA": "C_9VA",
    "C:AP Hill": "AP-Hill",
    "C:Armistead": "C_Armistead",
    "C:Art Res-1": "C_Art_Res-1",
    "C:Art Res-2": "C_Art_Res-2",
    "C:Art Res-3": "C_Art_Res-3",
    "C:Branch": "C_Branch",
    "C:Cavalry": "C_Cavalry",
    "C:Cobb-A": "C_Cobb-A",
    "C:Cobb-B": "C_Cobb-B",
    "C:Cobb-C": "C_Cobb-C",
    "C:Colston": "C_Colston",
    "C:Crump": "C_Crump",
    "C:DH Hill": "DH-Hill",
    "C:DR Jones": "C_DR_Jones",
    "C:DR Jones-A": "C_DR_Jones-A",
    "C:DR Jones-B": "C_DR_Jones-B",
    "C:DeSaussure": "C_DeSaussure",
    "C:Drayton": "C_Drayton",
    "C:Early-A": "C_Early-A",
    "C:Early-B": "C_Early-B",
    "C:Evans": "C_Evans",
    "C:Ewell": "C_Ewell",
    "C:Featherston": "C_Featherston",
    "C:Garland-A": "C_Garland-A",
    "C:Garland-B": "C_Garland-B",
    "C:Gregg": "C_Gregg",
    "C:Grifffith": "C_Grifffith",
    "C:Griffith": "C_Griffith",
    "C:Holmes": "C_Holmes",
    "C:Hood": "C_Hood",
    "C:Huger-A": "C_Huger-A",
    "C:Huger-B": "C_Huger-B",
    "C:JR Anderson": "C_JR_Anderson",
    "C:Jackson": "Jackson",
    "C:Johnston": "Johnston",
    "C:Kershaw": "C_Kershaw",
    "C:Lawton": "C_Lawton",
    "C:Lee": "Lee",
    "C:Longstreet": "Longstreet",
    "C:Magruder": "Magruder",
    "C:Mahone": "C_Mahone",
    "C:Martin": "C_Martin",
    "C:McLaws-A": "C_McLaws-A",
    "C:McLaws-B": "C_McLaws-B",
    "C:McLaws-C": "C_McLaws-C",
    "C:Pickett": "C_Pickett",
    "C:Pryor": "C_Pryor",
    "C:RH Anderson": "C_RH_Anderson",
    "C:Rains-A": "C_Rains-A",
    "C:Rains-B": "C_Rains-B",
    "C:Ransom": "C_Ransom",
    "C:Richmond-1": "C_Richmond-1",
    "C:Richmond-2": "C_Richmond-2",
    "C:Richmond-3": "C_Richmond-3",
    "C:Richmond-4": "C_Richmond-4",
    "C:Ripley": "C_Ripley",
    "C:Rodes-A": "C_Rodes-A",
    "C:Rodes-B": "C_Rodes-B",
    "C:Rodes-C": "C_Rodes-C",
    "C:Siege": "C_Siege",
    "C:Smith": "Smith",
    "C:Stuart": "Stuart",
    "C:T Anderson": "C_T_Anderson",
    "C:Toombs": "C_Toombs",
    "C:Walker": "C_Walker",
    "C:Ward": "C_Ward",
    "C:Whiting-A": "C_Whiting-A",
    "C:Whiting-B": "C_Whiting-B",
    "C:Wilcox-A": "C_Wilcox-A",
    "C:Wilcox-B": "C_Wilcox-B",
    "C:Winder": "C_Winder",
    "C:Wise-A": "C_Wise-A",
    "C:Wise-B": "C_Wise-B"
  },
  "matched_with_ext": {
    "U:1 NY": "U_1_NY.jpg",
    "U:1 NY Mrif": "U_1_NY_Mrif.jpg",
    "U:1 RI": "U_1_RI.jpg",
    "U:11 PA": "U_11_PA.jpg",
    "U:11/91 PA": "U_11-91_PA.jpg",
    "U:12/25 NY": "U_12-25_NY.jpg",
    "U:13 PA": "U_13_PA.jpg",
    "U:2 NY": "U_2_NY.jpg",
    "U:2DE/32MA": "U_2DE-32MA.jpg",
    "U:3/4 NY": "U_3-4_NY.jpg",
    "U:3/8 PA": "U_3-8_PA.jpg",
    "U:4 PA": "U_4_PA.jpg",
    "U:4PA": "U_4PA.jpg",
    "U:5 PA": "U_5_PA.jpg",
    "U:5/6 US": "U_5-6_US.jpg",
    "U:5/6US": "U_5-6US.jpg",
    "U:59/101 NY": "U_59-101_NY.jpg",
    "U:5MD/19WI": "U_5MD-19WI.jpg",
    "U:6 PA": "U_6_PA.jpg",
    "U:67/87 PA": "U_67-87_PA.jpg",
    "U:6PA": "U_6PA.jpg",
    "U:7/69 NY": "U_7-69_NY.jpg",
    "U:71/148 NY": "U_71-148_NY.jpg",
    "U:8 IL": "U_8_IL.jpg",
    "U:8IL": "U_8IL.jpg",
    "U:93 NY": "U_93_NY.jpg",
    "U:93NY": "U_93NY.jpg",
    "U:99/115 PA": "U_99-115_PA.jpg",
    "U:Art Res-1": "U_Art_Res-1.jpg",
    "U:Art Res-2": "U_Art_Res-2.jpg",
    "U:Buchanan": "U_Buchanan.jpg",
    "U:Burnside": "Burnside.jpg",
    "U:Carroll-A": "U_Carroll-A.jpg",
    "U:Carroll-B": "U_Carroll-B.jpg",
    "U:Casey": "U_Casey.jpg",
    "U:Couch": "U_Couch.jpg",
    "U:Doubleday": "U_Doubleday.jpg",
    "U:Ferry": "U_Ferry.jpg",
    "U:Foster": "U_Foster.jpg",
    "U:Franklin": "U_Franklin.jpg",
    "U:Hamilton": "U_Hamilton.jpg",
    "U:Heintzelman": "Heintzelman.jpg",
    "U:Hooker": "U_Hooker.jpg",
    "U:Horse Art": "U_Horse_Art.jpg",
    "U:Jameson": "U_Jameson.jpg",
    "U:Kearny": "U_Kearny.jpg",
    "U:Keyes": "Keyes.jpg",
    "U:Kimball": "U_Kimball.jpg",
    "U:King": "U_King.jpg",
    "U:McCall-A": "U_McCall-A.jpg",
    "U:McCall-B": "U_McCall-B.jpg",
    "U:McClellan": "McClelland.jpg",
    "U:McDowell": "McDowell.jpg",
    "U:Meade": "U_Meade.jpg",
    "U:Meagher": "U_Meagher.jpg",
    "U:Morell": "U_Morell.jpg",
    "U:Naglee-A": "U_Naglee-A.jpg",
    "U:Naglee-B": "U_Naglee-B.jpg",
    "U:Ord": "U_Ord.jpg",
    "U:Parke": "U_Parke.jpg",
    "U:Peck-A": "U_Peck-A.jpg",
    "U:Peck-B": "U_Peck-B.jpg",
    "U:Porter": "U_Porter.jpg",
    "U:Reno": "U_Reno.jpg",
    "U:Reynolds": "U_Reynolds.jpg",
    "U:Richardson": "U_Richardson.jpg",
    "U:Ricketts": "U_Ricketts.jpg",
    "U:Robinson": "U_Robinson.jpg",
    "U:Sedgwick": "U_Sedgwick.jpg",
    "U:Seymour": "U_Seymour.jpg",
    "U:Shields": "U_Shields.jpg",
    "U:Slocum": "U_Slocum.jpg",
    "U:Smith-A": "U_Smith-A.jpg",
    "U:Smith-B": "U_Smith-B.jpg",
    "U:Stevens": "U_Stevens.jpg",
    "U:Stoneman": "U_Stoneman.jpg",
    "U:Sumner": "Sumner.jpg",
    "U:Sykes-A": "U_Sykes-A.jpg",
    "U:Sykes-B": "U_Sykes-B.jpg",
    "U:Tyler": "U_Tyler.jpg",
    "U:Viele": "U_Viele.jpg",
    "U:Warren": "U_Warren.jpg",
    "U:Weber": "U_Weber.jpg",
    "U:Wright": "U_Wright.jpg",
    "C:1 NC": "C_1_NC.jpg",
    "C:1 VA": "C_1_VA.jpg",
    "C:10 GA": "C_10_GA.jpg",
    "C:10 VA": "C_10_VA.jpg",
    "C:13 VA": "C_13_VA.jpg",
    "C:14 SC": "C_14_SC.jpg",
    "C:2 VA": "C_2_VA.jpg",
    "C:22 VA": "C_22_VA.jpg",
    "C:28 VA": "C_28_VA.jpg",
    "C:2VA": "C_2VA.jpg",
    "C:3 VA": "C_3_VA.jpg",
    "C:32 NC": "C_32_NC.jpg",
    "C:4 VA": "C_4_VA.jpg",
    "C:4 VA HA": "C_4_VA_HA.jpg",
    "C:40VA": "C_40VA.jpg",
    "C:47 VA": "C_47_VA.jpg",
    "C:4VA": "C_4VA.jpg",
    "C:5 VA": "C_5_VA.jpg",
    "C:55 VA": "C_55_VA.jpg",
    "C:56 VA": "C_56_VA.jpg",
    "C:59 VA": "C_59_VA.jpg",
    "C:60 VA": "C_60_VA.jpg",
    "C:63 VA": "C_63_VA.jpg",
    "C:7 VA": "C_7_VA.jpg",
    "C:8 VA": "C_8_VA.jpg",
    "C:9 VA": "C_9_VA.jpg",
    "C:9VA": "C_9VA.jpg",
    "C:AP Hill": "AP-Hill.jpg",
    "C:Armistead": "C_Armistead.jpg",
    "C:Art Res-1": "C_Art_Res-1.jpg",
    "C:Art Res-2": "C_Art_Res-2.jpg",
    "C:Art Res-3": "C_Art_Res-3.jpg",
    "C:Branch": "C_Branch.jpg",
    "C:Cavalry": "C_Cavalry.jpg",
    "C:Cobb-A": "C_Cobb-A.jpg",
    "C:Cobb-B": "C_Cobb-B.jpg",
    "C:Cobb-C": "C_Cobb-C.jpg",
    "C:Colston": "C_Colston.jpg",
    "C:Crump": "C_Crump.jpg",
    "C:DH Hill": "DH-Hill.jpg",
    "C:DR Jones": "C_DR_Jones.jpg",
    "C:DR Jones-A": "C_DR_Jones-A.jpg",
    "C:DR Jones-B": "C_DR_Jones-B.jpg",
    "C:DeSaussure": "C_DeSaussure.jpg",
    "C:Drayton": "C_Drayton.jpg",
    "C:Early-A": "C_Early-A.jpg",
    "C:Early-B": "C_Early-B.jpg",
    "C:Evans": "C_Evans.jpg",
    "C:Ewell": "C_Ewell.jpg",
    "C:Featherston": "C_Featherston.jpg",
    "C:Garland-A": "C_Garland-A.jpg",
    "C:Garland-B": "C_Garland-B.jpg",
    "C:Gregg": "C_Gregg.jpg",
    "C:Grifffith": "C_Grifffith.jpg",
    "C:Griffith": "C_Griffith.jpg",
    "C:Holmes": "C_Holmes.jpg",
    "C:Hood": "C_Hood.jpg",
    "C:Huger-A": "C_Huger-A.jpg",
    "C:Huger-B": "C_Huger-B.jpg",
    "C:JR Anderson": "C_JR_Anderson.jpg",
    "C:Jackson": "Jackson.jpg",
    "C:Johnston": "Johnston.jpg",
    "C:Kershaw": "C_Kershaw.jpg",
    "C:Lawton": "C_Lawton.jpg",
    "C:Lee": "Lee.jpg",
    "C:Longstreet": "Longstreet.jpg",
    "C:Magruder": "Magruder.jpg",
    "C:Mahone": "C_Mahone.jpg",
    "C:Martin": "C_Martin.jpg",
    "C:McLaws-A": "C_McLaws-A.jpg",
    "C:McLaws-B": "C_McLaws-B.jpg",
    "C:McLaws-C": "C_McLaws-C.jpg",
    "C:Pickett": "C_Pickett.jpg",
    "C:Pryor": "C_Pryor.jpg",
    "C:RH Anderson": "C_RH_Anderson.jpg",
    "C:Rains-A": "C_Rains-A.jpg",
    "C:Rains-B": "C_Rains-B.jpg",
    "C:Ransom": "C_Ransom.jpg",
    "C:Richmond-1": "C_Richmond-1.jpg",
    "C:Richmond-2": "C_Richmond-2.jpg",
    "C:Richmond-3": "C_Richmond-3.jpg",
    "C:Richmond-4": "C_Richmond-4.jpg",
    "C:Ripley": "C_Ripley.jpg",
    "C:Rodes-A": "C_Rodes-A.jpg",
    "C:Rodes-B": "C_Rodes-B.jpg",
    "C:Rodes-C": "C_Rodes-C.jpg",
    "C:Siege": "C_Siege.jpg",
    "C:Smith": "Smith.jpg",
    "C:Stuart": "Stuart.jpg",
    "C:T Anderson": "C_T_Anderson.jpg",
    "C:Toombs": "C_Toombs.jpg",
    "C:Walker": "C_Walker.jpg",
    "C:Ward": "C_Ward.jpg",
    "C:Whiting-A": "C_Whiting-A.jpg",
    "C:Whiting-B": "C_Whiting-B.jpg",
    "C:Wilcox-A": "C_Wilcox-A.jpg",
    "C:Wilcox-B": "C_Wilcox-B.jpg",
    "C:Winder": "C_Winder.jpg",
    "C:Wise-A": "C_Wise-A.jpg",
    "C:Wise-B": "C_Wise-B.jpg"
  },
  "unmatched": [],
  "unused_images": [],
  "note": "Generated by generate_counters.py for otr2"
}